{"code": "0", "msg": "success", "data": {"ex": [{"number": 634, "shortRate": 5.64, "longRate": 94.36, "longVolUsd": 1521519.33654186, "rate": 100, "shortVolUsd": 90947.56999936, "exchangeName": "All", "totalVolUsd": 1612466.90654122, "averagePrice": 2543.3232, "exchangeLogo": "https://cdn.sampyun.com/static/blank.png"}, {"number": 304, "shortRate": 2.06, "longRate": 97.94, "longVolUsd": 720671.59253, "rate": 45.63, "shortVolUsd": 15125.8317, "exchangeName": "Binance", "totalVolUsd": 735797.42423, "averagePrice": 2420.3863, "exchangeLogo": "https://cdn.coinglasscdn.com/static/exchanges/270.png"}, {"number": 106, "shortRate": 8.54, "longRate": 91.46, "longVolUsd": 268320.9334, "rate": 18.2, "shortVolUsd": 25068.5318, "exchangeName": "Bybit", "totalVolUsd": 293389.4652, "averagePrice": 2767.8251, "exchangeLogo": "https://cdn.coinglasscdn.com/static/exchanges/521.png"}, {"number": 46, "shortRate": 6.4, "longRate": 93.6, "longVolUsd": 209768.2945, "rate": 13.9, "shortVolUsd": 14339.26, "exchangeName": "Huobi", "totalVolUsd": 224107.5545, "averagePrice": 4871.9034, "exchangeLogo": "https://cdn.coinglasscdn.com/static/exchanges/2502.png"}, {"number": 86, "shortRate": 0.0, "longRate": 100.0, "longVolUsd": 203777.05676606, "rate": 12.64, "shortVolUsd": 0, "exchangeName": "CoinEx", "totalVolUsd": 203777.05676606, "averagePrice": 2369.5007, "exchangeLogo": "https://cdn.sampyun.com/static/exchanges/CoinEx.png"}, {"number": 24, "shortRate": 0.0, "longRate": 100.0, "longVolUsd": 97880.913, "rate": 6.07, "shortVolUsd": 0, "exchangeName": "OKX", "totalVolUsd": 97880.913, "averagePrice": 4078.3714, "exchangeLogo": "https://cdn.coinglasscdn.com/static/exchanges/OKX.png"}, {"number": 60, "shortRate": 100.0, "longRate": 0.0, "longVolUsd": 0, "rate": 2.26, "shortVolUsd": 36413.94649936, "exchangeName": "Bitfinex", "totalVolUsd": 36413.94649936, "averagePrice": 606.8991, "exchangeLogo": "https://cdn.coinglasscdn.com/static/exchanges/bitfinex.jpg"}, {"number": 8, "shortRate": 0.0, "longRate": 100.0, "longVolUsd": 21100.5463458, "rate": 1.31, "shortVolUsd": 0, "exchangeName": "Bitmex", "totalVolUsd": 21100.5463458, "averagePrice": 2637.5683, "exchangeLogo": "https://cdn.coinglasscdn.com/static/exchanges/157.png"}, {"number": 0, "shortRate": 0, "amount": 0, "longRate": 0, "rate": 0, "exchangeName": "Deribit", "totalVolUsd": 0, "averagePrice": 0, "exchangeLogo": "https://cdn.coinglasscdn.com/static/exchanges/deribit.png"}], "info": {"h1TotalVolUsd": 72907266.0335633, "h1Amount": 0, "h4TotalVolUsd": 76263779.55242853, "h4Amount": 0, "h12TotalVolUsd": 85059121.71327811, "h12Amount": 0, "h24TotalVolUsd": 107248418.57762343, "h24Amount": 0, "h24Chain": 43.42, "liquidationH24Num": 30733, "maxLiquidationOrder": {"id": 70562020, "exchangeName": "Binance", "originalSymbol": "ETHUSDT", "symbol": "ETH", "price": 1204.0, "qty": 4586.925, "volUsd": 5522657.7, "side": 1, "type": 1, "turnoverTime": 1671181248775, "createTime": 1671181249000, "quoteCurrency": "USDT", "exchangeLogo": "https://cdn.coinglasscdn.com/static/exchanges/270.png", "symbolLogo": "https://cdn.coinglasscdn.com/static/coins/eth@2x.png"}}, "coin": [{"number": 3277, "symbol": "ETH", "amount": 32294.7339, "longVolUsd": 1549909.12040612, "shortVolUsd": 37642011.05317542, "symbolLogo": "https://cdn.coinglasscdn.com/static/coins/eth@2x.png", "totalVolUsd": 39191920.17358154}, {"number": 2879, "symbol": "BTC", "amount": 1838.4292, "longVolUsd": 2936198.86432198, "shortVolUsd": 28417475.25010085, "symbolLogo": "https://cdn.coinglasscdn.com/static/coins/btc@2x.png", "totalVolUsd": 31353674.11442283}, {"number": 1172, "symbol": "DOGE", "amount": 39990958.6327, "longVolUsd": 235921.40799796, "shortVolUsd": 3054534.66829506, "symbolLogo": "https://cdn.coinglasscdn.com/static/coins/doge.png", "totalVolUsd": 3290456.07629302}, {"number": 907, "symbol": "LTC", "amount": 43136.5972, "longVolUsd": 22746.09585, "shortVolUsd": 2968776.91726075, "symbolLogo": "https://cdn.coinglasscdn.com/static/coins/ltc@2x.png", "totalVolUsd": 2991523.01311075}, {"number": 745, "symbol": "FIL", "amount": 490699.5987, "longVolUsd": 6926.498702, "shortVolUsd": 1903857.73863355, "symbolLogo": "https://cdn.coinglasscdn.com/static/coins/filecoin.webp", "totalVolUsd": 1910784.23733555}, {"number": 634, "symbol": "XRP", "amount": 4425355.8376, "longVolUsd": 90947.56999936, "shortVolUsd": 1521519.33654186, "symbolLogo": "https://cdn.coinglasscdn.com/static/coins/xrp@2x.png", "totalVolUsd": 1612466.90654122}, {"number": 932, "symbol": "BNB", "amount": 5997.9061, "longVolUsd": 412342.79807, "shortVolUsd": 1113824.40481343, "symbolLogo": "https://cdn.coinglasscdn.com/static/coins/bnb.png", "totalVolUsd": 1526167.20288343}, {"number": 512, "symbol": "LINK", "amount": 218852.1949, "longVolUsd": 13006.22955154, "shortVolUsd": 1350005.24001898, "symbolLogo": "https://cdn.coinglasscdn.com/static/coins/link@2x.png", "totalVolUsd": 1363011.46957052}, {"number": 910, "symbol": "ADA", "amount": 4389141.2309, "longVolUsd": 7716.21829032, "shortVolUsd": 1254161.88557804, "symbolLogo": "https://cdn.coinglasscdn.com/static/coins/ada.png", "totalVolUsd": 1261878.10386836}, {"number": 333, "symbol": "ETC", "amount": 70790.3819, "longVolUsd": 3707.75939172, "shortVolUsd": 1231159.66159076, "symbolLogo": "https://cdn.coinglasscdn.com/static/coins/etc@2x.png", "totalVolUsd": 1234867.42098248}, {"number": 99, "symbol": "TESTBTC", "longVolUsd": 934389.5099693, "shortVolUsd": 0, "symbolLogo": "https://cdn.sampyun.com/static/blank.png", "totalVolUsd": 934389.5099693}, {"number": 379, "symbol": "APE", "amount": 236453.255, "longVolUsd": 141887.15268771, "shortVolUsd": 776260.83636391, "symbolLogo": "https://cdn.coinglasscdn.com/static/coins/apecoin.png", "totalVolUsd": 918147.98905162}]}, "success": true}