{"code": "0", "msg": "success", "data": [{"symbol": "BRZ", "longRate": 89.14, "longVolUsd": 129.4022, "shortRate": 10.86, "shortVolUsd": 15.7573, "exchangeLogo": "https://cdn.sampyun.com/static/blank.png", "symbolLogo": "https://cdn.coinglasscdn.com/static/coins/brz.webp", "totalVolUsd": 145.1595, "list": [{"exchangeName": "FTX", "symbol": "BRZ", "updateTime": 1664720468692, "turnoverNumber": 5, "longRate": 89.14, "longVolUsd": 129.4022, "shortRate": 10.86, "shortVolUsd": 15.7573, "exchangeLogo": "https://cdn.coinglasscdn.com/static/exchanges/524.png", "symbolLogo": "https://cdn.coinglasscdn.com/static/coins/brz.webp", "totalVolUsd": 145.1595, "buyTurnoverNumber": 3, "sellTurnoverNumber": 2}]}], "success": true}