{"code": "0", "msg": "success", "data": [{"symbol": "EOS", "longRate": 56.46, "longVolUsd": 164407.6774, "shortRate": 43.54, "shortVolUsd": 126803.6962, "exchangeLogo": "https://cdn.sampyun.com/static/blank.png", "symbolLogo": "https://cdn.coinglasscdn.com/static/coins/eos@2x.png", "totalVolUsd": 291211.3736, "list": [{"exchangeName": "Binance", "symbol": "EOS", "updateTime": 1673030265358, "turnoverNumber": 401, "longRate": 55.8, "longVolUsd": 121578.1801, "shortRate": 44.2, "shortVolUsd": 96286.2385, "exchangeLogo": "https://cdn.coinglasscdn.com/static/exchanges/270.png", "symbolLogo": "https://cdn.coinglasscdn.com/static/coins/eos@2x.png", "totalVolUsd": 217864.4186, "buyTurnoverNumber": 232, "sellTurnoverNumber": 169}, {"exchangeName": "OKX", "symbol": "EOS", "updateTime": 1673030265358, "turnoverNumber": 350, "longRate": 53.52, "longVolUsd": 24900.752, "shortRate": 46.48, "shortVolUsd": 21628.01, "exchangeLogo": "https://cdn.coinglasscdn.com/static/exchanges/OKX.png", "symbolLogo": "https://cdn.coinglasscdn.com/static/coins/eos@2x.png", "totalVolUsd": 46528.762, "buyTurnoverNumber": 172, "sellTurnoverNumber": 178}, {"exchangeName": "Bitget", "symbol": "EOS", "updateTime": 1673030265358, "turnoverNumber": 289, "longRate": 54.71, "longVolUsd": 8002.1922, "shortRate": 45.29, "shortVolUsd": 6625.5984, "exchangeLogo": "https://cdn.coinglasscdn.com/static/exchanges/bitget3.png", "symbolLogo": "https://cdn.coinglasscdn.com/static/coins/eos@2x.png", "totalVolUsd": 14627.7906, "buyTurnoverNumber": 157, "sellTurnoverNumber": 132}, {"exchangeName": "CoinEx", "symbol": "EOS", "updateTime": 1673030266530, "turnoverNumber": 23, "longRate": 84.78, "longVolUsd": 5592.2699, "shortRate": 15.22, "shortVolUsd": 1004.23, "exchangeLogo": "https://cdn.sampyun.com/static/exchanges/CoinEx.png", "symbolLogo": "https://cdn.coinglasscdn.com/static/coins/eos@2x.png", "totalVolUsd": 6596.4999, "buyTurnoverNumber": 16, "sellTurnoverNumber": 7}, {"exchangeName": "dYdX", "symbol": "EOS", "updateTime": 1673030266530, "turnoverNumber": 0, "longRate": 0, "longVolUsd": 0.0, "shortRate": 0, "shortVolUsd": 0.0, "exchangeLogo": "https://cdn.coinglasscdn.com/static/coins/DYDX.png", "symbolLogo": "https://cdn.coinglasscdn.com/static/coins/eos@2x.png", "totalVolUsd": 0.0, "buyTurnoverNumber": 0, "sellTurnoverNumber": 0}, {"exchangeName": "Bitmex", "symbol": "EOS", "updateTime": 1673030265358, "turnoverNumber": 0, "longRate": 0, "longVolUsd": 0.0, "shortRate": 0, "shortVolUsd": 0.0, "exchangeLogo": "https://cdn.coinglasscdn.com/static/exchanges/157.png", "symbolLogo": "https://cdn.coinglasscdn.com/static/coins/eos@2x.png", "totalVolUsd": 0.0, "buyTurnoverNumber": 0, "sellTurnoverNumber": 0}, {"exchangeName": "Bybit", "symbol": "EOS", "updateTime": 1673030265358, "turnoverNumber": 22, "longRate": 83.83, "longVolUsd": 3604.1544, "shortRate": 16.17, "shortVolUsd": 695.1523, "exchangeLogo": "https://cdn.coinglasscdn.com/static/exchanges/521.png", "symbolLogo": "https://cdn.coinglasscdn.com/static/coins/eos@2x.png", "totalVolUsd": 4299.3067, "buyTurnoverNumber": 16, "sellTurnoverNumber": 6}, {"exchangeName": "Huobi", "symbol": "EOS", "updateTime": 1673030266530, "turnoverNumber": 12, "longRate": 56.44, "longVolUsd": 730.1288, "shortRate": 43.56, "shortVolUsd": 563.467, "exchangeLogo": "https://cdn.coinglasscdn.com/static/exchanges/2502.png", "symbolLogo": "https://cdn.coinglasscdn.com/static/coins/eos@2x.png", "totalVolUsd": 1293.5958, "buyTurnoverNumber": 8, "sellTurnoverNumber": 4}, {"exchangeName": "Kraken", "symbol": "EOS", "updateTime": 1660286279328, "turnoverNumber": 1, "longRate": 0.0, "longVolUsd": 0.0, "shortRate": 100.0, "shortVolUsd": 1.0, "exchangeLogo": "https://cdn.coinglasscdn.com/static/exchanges/k.jpg", "symbolLogo": "https://cdn.coinglasscdn.com/static/coins/eos@2x.png", "totalVolUsd": 1.0, "buyTurnoverNumber": 0, "sellTurnoverNumber": 1}]}], "success": true}