{"code": "0", "msg": "success", "data": [{"symbol": "LPT", "longRate": 55.61, "longVolUsd": 6809.7115, "shortRate": 44.39, "shortVolUsd": 5434.8682, "exchangeLogo": "https://cdn.sampyun.com/static/blank.png", "symbolLogo": "https://cdn.coinglasscdn.com/static/coins/lpt.png", "totalVolUsd": 12244.5797, "list": [{"exchangeName": "Binance", "symbol": "LPT", "updateTime": 1664720394436, "turnoverNumber": 87, "longRate": 50.04, "longVolUsd": 5385.9695, "shortRate": 49.96, "shortVolUsd": 5377.1177, "exchangeLogo": "https://cdn.coinglasscdn.com/static/exchanges/270.png", "symbolLogo": "https://cdn.coinglasscdn.com/static/coins/lpt.png", "totalVolUsd": 10763.0872, "buyTurnoverNumber": 62, "sellTurnoverNumber": 25}, {"exchangeName": "Okex", "symbol": "LPT", "updateTime": 1664720394436, "turnoverNumber": 7, "longRate": 100.0, "longVolUsd": 1330.224, "shortRate": 0.0, "shortVolUsd": 0.0, "exchangeLogo": "https://cdn.coinglasscdn.com/static/exchanges/OKX.png", "symbolLogo": "https://cdn.coinglasscdn.com/static/coins/lpt.png", "totalVolUsd": 1330.224, "buyTurnoverNumber": 7, "sellTurnoverNumber": 0}, {"exchangeName": "CoinEx", "symbol": "LPT", "updateTime": 1664720394436, "turnoverNumber": 4, "longRate": 100.0, "longVolUsd": 44.4699, "shortRate": 0.0, "shortVolUsd": 0.0, "exchangeLogo": "https://cdn.sampyun.com/static/exchanges/CoinEx.png", "symbolLogo": "https://cdn.coinglasscdn.com/static/coins/lpt.png", "totalVolUsd": 44.4699, "buyTurnoverNumber": 4, "sellTurnoverNumber": 0}, {"exchangeName": "Bybit", "symbol": "LPT", "updateTime": 1664720394436, "turnoverNumber": 2, "longRate": 70.71, "longVolUsd": 10.68, "shortRate": 29.29, "shortVolUsd": 4.425, "exchangeLogo": "https://cdn.coinglasscdn.com/static/exchanges/521.png", "symbolLogo": "https://cdn.coinglasscdn.com/static/coins/lpt.png", "totalVolUsd": 15.105, "buyTurnoverNumber": 1, "sellTurnoverNumber": 1}, {"exchangeName": "Huobi", "symbol": "LPT", "updateTime": 1664720394436, "turnoverNumber": 3, "longRate": 42.49, "longVolUsd": 38.3681, "shortRate": 57.51, "shortVolUsd": 51.9255, "exchangeLogo": "https://cdn.coinglasscdn.com/static/exchanges/2502.png", "symbolLogo": "https://cdn.coinglasscdn.com/static/coins/lpt.png", "totalVolUsd": 90.2936, "buyTurnoverNumber": 2, "sellTurnoverNumber": 1}, {"exchangeName": "Kraken", "symbol": "LPT", "updateTime": 1660283459542, "turnoverNumber": 1, "longRate": 0.0, "longVolUsd": 0.0, "shortRate": 100.0, "shortVolUsd": 1.4, "exchangeLogo": "https://cdn.coinglasscdn.com/static/exchanges/k.jpg", "symbolLogo": "https://cdn.coinglasscdn.com/static/coins/lpt.png", "totalVolUsd": 1.4, "buyTurnoverNumber": 0, "sellTurnoverNumber": 1}]}], "success": true}