{"code": "0", "msg": "success", "data": [{"symbol": "LUNC", "longRate": 57.3, "longVolUsd": 17032.4695, "shortRate": 42.7, "shortVolUsd": 12692.5521, "exchangeLogo": "https://cdn.sampyun.com/static/blank.png", "symbolLogo": "https://cdn.coinglasscdn.com/static/coins/luna1557227471663.webp", "totalVolUsd": 29725.0216, "list": [{"exchangeName": "Okex", "symbol": "LUNC", "updateTime": 1668597990095, "turnoverNumber": 157, "longRate": 61.77, "longVolUsd": 14011.0747, "shortRate": 38.23, "shortVolUsd": 8672.7428, "exchangeLogo": "https://cdn.coinglasscdn.com/static/exchanges/OKX.png", "symbolLogo": "https://cdn.coinglasscdn.com/static/coins/luna1557227471663.webp", "totalVolUsd": 22683.8175, "buyTurnoverNumber": 91, "sellTurnoverNumber": 66}, {"exchangeName": "Bitget", "symbol": "LUNC", "updateTime": 1668597990095, "turnoverNumber": 84, "longRate": 62.62, "longVolUsd": 695.4954, "shortRate": 37.38, "shortVolUsd": 415.173, "exchangeLogo": "https://cdn.coinglasscdn.com/static/exchanges/bitget3.png", "symbolLogo": "https://cdn.coinglasscdn.com/static/coins/luna1557227471663.webp", "totalVolUsd": 1110.6684, "buyTurnoverNumber": 45, "sellTurnoverNumber": 39}, {"exchangeName": "CoinEx", "symbol": "LUNC", "updateTime": 1668597990095, "turnoverNumber": 40, "longRate": 37.58, "longVolUsd": 2141.2552, "shortRate": 62.42, "shortVolUsd": 3556.67, "exchangeLogo": "https://cdn.sampyun.com/static/exchanges/CoinEx.png", "symbolLogo": "https://cdn.coinglasscdn.com/static/coins/luna1557227471663.webp", "totalVolUsd": 5697.9252, "buyTurnoverNumber": 16, "sellTurnoverNumber": 24}, {"exchangeName": "Huobi", "symbol": "LUNC", "updateTime": 1668597990095, "turnoverNumber": 22, "longRate": 79.38, "longVolUsd": 184.6442, "shortRate": 20.62, "shortVolUsd": 47.9663, "exchangeLogo": "https://cdn.coinglasscdn.com/static/exchanges/2502.png", "symbolLogo": "https://cdn.coinglasscdn.com/static/coins/luna1557227471663.webp", "totalVolUsd": 232.6105, "buyTurnoverNumber": 15, "sellTurnoverNumber": 7}]}], "success": true}