{"code": "0", "msg": "success", "data": [{"symbol": "LUNC", "longRate": 41.39, "longVolUsd": 345954.8779, "shortRate": 58.61, "shortVolUsd": 489966.0092, "exchangeLogo": "https://cdn.sampyun.com/static/blank.png", "symbolLogo": "https://cdn.coinglasscdn.com/static/coins/luna1557227471663.webp", "totalVolUsd": 835920.8871, "list": [{"exchangeName": "Okex", "symbol": "LUNC", "updateTime": 1664720270822, "turnoverNumber": 1162, "longRate": 40.52, "longVolUsd": 168983.3183, "shortRate": 59.48, "shortVolUsd": 248081.5715, "exchangeLogo": "https://cdn.coinglasscdn.com/static/exchanges/OKX.png", "symbolLogo": "https://cdn.coinglasscdn.com/static/coins/luna1557227471663.webp", "totalVolUsd": 417064.8898, "buyTurnoverNumber": 534, "sellTurnoverNumber": 628}, {"exchangeName": "Bitget", "symbol": "LUNC", "updateTime": 1664720270822, "turnoverNumber": 166, "longRate": 21.86, "longVolUsd": 28587.0292, "shortRate": 78.14, "shortVolUsd": 102156.3653, "exchangeLogo": "https://cdn.coinglasscdn.com/static/exchanges/bitget3.png", "symbolLogo": "https://cdn.coinglasscdn.com/static/coins/luna1557227471663.webp", "totalVolUsd": 130743.3945, "buyTurnoverNumber": 84, "sellTurnoverNumber": 82}, {"exchangeName": "FTX", "symbol": "LUNC", "updateTime": 1664720270822, "turnoverNumber": 686, "longRate": 49.3, "longVolUsd": 94257.6424, "shortRate": 50.7, "shortVolUsd": 96921.9531, "exchangeLogo": "https://cdn.coinglasscdn.com/static/exchanges/524.png", "symbolLogo": "https://cdn.coinglasscdn.com/static/coins/luna1557227471663.webp", "totalVolUsd": 191179.5955, "buyTurnoverNumber": 267, "sellTurnoverNumber": 419}, {"exchangeName": "CoinEx", "symbol": "LUNC", "updateTime": 1664720270822, "turnoverNumber": 45, "longRate": 68.25, "longVolUsd": 8993.858, "shortRate": 31.75, "shortVolUsd": 4184.3448, "exchangeLogo": "https://cdn.sampyun.com/static/exchanges/CoinEx.png", "symbolLogo": "https://cdn.coinglasscdn.com/static/coins/luna1557227471663.webp", "totalVolUsd": 13178.2028, "buyTurnoverNumber": 22, "sellTurnoverNumber": 23}, {"exchangeName": "Huobi", "symbol": "LUNC", "updateTime": 1664720270822, "turnoverNumber": 135, "longRate": 53.89, "longVolUsd": 45133.03, "shortRate": 46.11, "shortVolUsd": 38621.7745, "exchangeLogo": "https://cdn.coinglasscdn.com/static/exchanges/2502.png", "symbolLogo": "https://cdn.coinglasscdn.com/static/coins/luna1557227471663.webp", "totalVolUsd": 83754.8045, "buyTurnoverNumber": 57, "sellTurnoverNumber": 78}]}], "success": true}