{"code": "0", "msg": "success", "data": [{"symbol": "MAGIC", "longRate": 68.59, "longVolUsd": 148979.3164, "shortRate": 31.41, "shortVolUsd": 68215.9702, "exchangeLogo": "https://cdn.sampyun.com/static/blank.png", "symbolLogo": "https://cdn.sampyun.com/static/blank.png", "totalVolUsd": 217195.2866, "list": [{"exchangeName": "Bybit", "symbol": "MAGIC", "updateTime": 1671182539892, "turnoverNumber": 1197, "longRate": 68.59, "longVolUsd": 148979.3164, "shortRate": 31.41, "shortVolUsd": 68215.9702, "exchangeLogo": "https://cdn.coinglasscdn.com/static/exchanges/521.png", "symbolLogo": "https://cdn.sampyun.com/static/blank.png", "totalVolUsd": 217195.2866, "buyTurnoverNumber": 740, "sellTurnoverNumber": 457}]}], "success": true}