{"code": "0", "msg": "success", "data": [{"symbol": "TWT", "longRate": 44.8, "longVolUsd": 19110.6667, "shortRate": 55.2, "shortVolUsd": 23546.3622, "exchangeLogo": "https://cdn.sampyun.com/static/blank.png", "symbolLogo": "https://cdn.sampyun.com/static/blank.png", "totalVolUsd": 42657.0289, "list": [{"exchangeName": "Bybit", "symbol": "TWT", "updateTime": 1673030394286, "turnoverNumber": 140, "longRate": 44.8, "longVolUsd": 19110.6667, "shortRate": 55.2, "shortVolUsd": 23546.3622, "exchangeLogo": "https://cdn.coinglasscdn.com/static/exchanges/521.png", "symbolLogo": "https://cdn.sampyun.com/static/blank.png", "totalVolUsd": 42657.0289, "buyTurnoverNumber": 82, "sellTurnoverNumber": 58}]}], "success": true}