{"code": "0", "msg": "success", "data": [{"symbol": "UNFI", "longRate": 46.18, "longVolUsd": 167024.8121, "shortRate": 53.82, "shortVolUsd": 194690.4152, "exchangeLogo": "https://cdn.sampyun.com/static/blank.png", "symbolLogo": "https://cdn.coinglasscdn.com/static/coins/UNFI.webp", "totalVolUsd": 361715.2273, "list": [{"exchangeName": "Binance", "symbol": "UNFI", "updateTime": 1671182470757, "turnoverNumber": 1167, "longRate": 49.09, "longVolUsd": 133284.7854, "shortRate": 50.91, "shortVolUsd": 138243.1411, "exchangeLogo": "https://cdn.coinglasscdn.com/static/exchanges/270.png", "symbolLogo": "https://cdn.coinglasscdn.com/static/coins/UNFI.webp", "totalVolUsd": 271527.9265, "buyTurnoverNumber": 647, "sellTurnoverNumber": 520}, {"exchangeName": "Bybit", "symbol": "UNFI", "updateTime": 1671182470757, "turnoverNumber": 208, "longRate": 37.41, "longVolUsd": 33740.0267, "shortRate": 62.59, "shortVolUsd": 56447.2741, "exchangeLogo": "https://cdn.coinglasscdn.com/static/exchanges/521.png", "symbolLogo": "https://cdn.coinglasscdn.com/static/coins/UNFI.webp", "totalVolUsd": 90187.3008, "buyTurnoverNumber": 98, "sellTurnoverNumber": 110}, {"exchangeName": "Huobi", "symbol": "UNFI", "updateTime": 1666742639725, "turnoverNumber": 0, "longRate": 0, "longVolUsd": 0.0, "shortRate": 0, "shortVolUsd": 0.0, "exchangeLogo": "https://cdn.coinglasscdn.com/static/exchanges/2502.png", "symbolLogo": "https://cdn.coinglasscdn.com/static/coins/UNFI.webp", "totalVolUsd": 0.0, "buyTurnoverNumber": 0, "sellTurnoverNumber": 0}]}], "success": true}