{"code": "0", "msg": "success", "data": [{"symbol": "XCH", "longRate": 96.61, "longVolUsd": 768.8186, "shortRate": 3.39, "shortVolUsd": 26.9499, "exchangeLogo": "https://cdn.sampyun.com/static/blank.png", "symbolLogo": "https://cdn.coinglasscdn.com/static/coins/XCH.png", "totalVolUsd": 795.7685, "list": [{"exchangeName": "Okex", "symbol": "XCH", "updateTime": 1668598108278, "turnoverNumber": 37, "longRate": 96.61, "longVolUsd": 768.8186, "shortRate": 3.39, "shortVolUsd": 26.9499, "exchangeLogo": "https://cdn.coinglasscdn.com/static/exchanges/OKX.png", "symbolLogo": "https://cdn.coinglasscdn.com/static/coins/XCH.png", "totalVolUsd": 795.7685, "buyTurnoverNumber": 29, "sellTurnoverNumber": 8}]}], "success": true}