{"code": "0", "msg": "success", "data": [{"symbol": "YFII", "longRate": 56.21, "longVolUsd": 416738.1604, "shortRate": 43.79, "shortVolUsd": 324658.8384, "exchangeLogo": "https://cdn.sampyun.com/static/blank.png", "symbolLogo": "https://cdn.coinglasscdn.com/static/coins/yfii.png", "totalVolUsd": 741396.9988, "list": [{"exchangeName": "Binance", "symbol": "YFII", "updateTime": 1649753880110, "turnoverNumber": 3, "longRate": 100.0, "longVolUsd": 207.4452, "shortRate": 0.0, "shortVolUsd": 0.0, "exchangeLogo": "https://cdn.coinglasscdn.com/static/exchanges/270.png", "symbolLogo": "https://cdn.coinglasscdn.com/static/coins/yfii.png", "totalVolUsd": 207.4452, "buyTurnoverNumber": 3, "sellTurnoverNumber": 0}, {"exchangeName": "Okex", "symbol": "YFII", "updateTime": 1668597933262, "turnoverNumber": 3334, "longRate": 56.13, "longVolUsd": 403419.1946, "shortRate": 43.87, "shortVolUsd": 315303.9331, "exchangeLogo": "https://cdn.coinglasscdn.com/static/exchanges/OKX.png", "symbolLogo": "https://cdn.coinglasscdn.com/static/coins/yfii.png", "totalVolUsd": 718723.1277, "buyTurnoverNumber": 1769, "sellTurnoverNumber": 1565}, {"exchangeName": "Huobi", "symbol": "YFII", "updateTime": 1668597933262, "turnoverNumber": 92, "longRate": 58.36, "longVolUsd": 13111.5206, "shortRate": 41.64, "shortVolUsd": 9354.9053, "exchangeLogo": "https://cdn.coinglasscdn.com/static/exchanges/2502.png", "symbolLogo": "https://cdn.coinglasscdn.com/static/coins/yfii.png", "totalVolUsd": 22466.4259, "buyTurnoverNumber": 54, "sellTurnoverNumber": 38}]}], "success": true}